[
  {
    "date": "2021-04-23",
    "volume": 5013860795.8,
    "txCount": 5277
  },
  {
    "date": "2021-04-24",
    "volume": 242975947.84,
    "txCount": 2485
  },
  {
    "date": "2021-04-25",
    "volume": 146678946.94,
    "txCount": 1970
  },
  {
    "date": "2021-04-26",
    "volume": 116615749.05,
    "txCount": 1451
  },
  {
    "date": "2021-04-27",
    "volume": 67696171.66,
    "txCount": 865
  },
  {
    "date": "2021-04-28",
    "volume": 59652707.46,
    "txCount": 553
  },
  {
    "date": "2021-04-29",
    "volume": 44465215.21,
    "txCount": 463
  },
  {
    "date": "2021-04-30",
    "volume": 38139387.75,
    "txCount": 711
  },
  {
    "date": "2021-05-01",
    "volume": 25995007.4,
    "txCount": 418
  },
  {
    "date": "2021-05-02",
    "volume": 44028044.58,
    "txCount": 437
  },
  {
    "date": "2021-05-03",
    "volume": 18950655.21,
    "txCount": 437
  },
  {
    "date": "2021-05-04",
    "volume": 41029051.01,
    "txCount": 486
  },
  {
    "date": "2021-05-05",
    "volume": 59045940.02,
    "txCount": 377
  },
  {
    "date": "2021-05-06",
    "volume": 71100100.47,
    "txCount": 348
  },
  {
    "date": "2021-05-07",
    "volume": 29644261.39,
    "txCount": 335
  },
  {
    "date": "2021-05-08",
    "volume": 31337110.4,
    "txCount": 427
  },
  {
    "date": "2021-05-09",
    "volume": 41965367.36,
    "txCount": 436
  },
  {
    "date": "2021-05-10",
    "volume": 21726572.22,
    "txCount": 235
  },
  {
    "date": "2021-05-11",
    "volume": 34796744.44,
    "txCount": 329
  },
  {
    "date": "2021-05-12",
    "volume": 46855944,
    "txCount": 640
  },
  {
    "date": "2021-05-13",
    "volume": 19139919.8,
    "txCount": 244
  },
  {
    "date": "2021-05-14",
    "volume": 66900006.47,
    "txCount": 189
  },
  {
    "date": "2021-05-15",
    "volume": 23246767.57,
    "txCount": 260
  },
  {
    "date": "2021-05-16",
    "volume": 16872935.5,
    "txCount": 222
  },
  {
    "date": "2021-05-17",
    "volume": 16849391.52,
    "txCount": 140
  },
  {
    "date": "2021-05-18",
    "volume": 18082482.76,
    "txCount": 174
  },
  {
    "date": "2021-05-19",
    "volume": 47544547.89,
    "txCount": 218
  },
  {
    "date": "2021-05-20",
    "volume": 20274377.48,
    "txCount": 201
  },
  {
    "date": "2021-05-21",
    "volume": 19106726.76,
    "txCount": 131
  },
  {
    "date": "2021-05-22",
    "volume": 20084263.46,
    "txCount": 175
  },
  {
    "date": "2021-05-23",
    "volume": 42546557.45,
    "txCount": 452
  },
  {
    "date": "2021-05-24",
    "volume": 13318884.3,
    "txCount": 238
  },
  {
    "date": "2021-05-25",
    "volume": 12607184.94,
    "txCount": 194
  },
  {
    "date": "2021-05-26",
    "volume": 20308468.25,
    "txCount": 228
  },
  {
    "date": "2021-05-27",
    "volume": 8366379.02,
    "txCount": 112
  },
  {
    "date": "2021-05-28",
    "volume": 8390398.08,
    "txCount": 96
  },
  {
    "date": "2021-05-29",
    "volume": 17706111.77,
    "txCount": 184
  },
  {
    "date": "2021-05-30",
    "volume": 4971358.97,
    "txCount": 59
  },
  {
    "date": "2021-05-31",
    "volume": 9139926.01,
    "txCount": 75
  },
  {
    "date": "2021-06-01",
    "volume": 14357243.28,
    "txCount": 58
  },
  {
    "date": "2021-06-02",
    "volume": 7656389.02,
    "txCount": 66
  },
  {
    "date": "2021-06-03",
    "volume": 6312214.64,
    "txCount": 80
  },
  {
    "date": "2021-06-04",
    "volume": 4111135.62,
    "txCount": 48
  },
  {
    "date": "2021-06-05",
    "volume": 8818477.18,
    "txCount": 43
  },
  {
    "date": "2021-06-06",
    "volume": 2960730.43,
    "txCount": 50
  },
  {
    "date": "2021-06-07",
    "volume": 6688530.56,
    "txCount": 41
  },
  {
    "date": "2021-06-08",
    "volume": 19134637.65,
    "txCount": 48
  },
  {
    "date": "2021-06-09",
    "volume": 1246630.73,
    "txCount": 53
  },
  {
    "date": "2021-06-10",
    "volume": 17144227.71,
    "txCount": 43
  },
  {
    "date": "2021-06-11",
    "volume": 12107550.8,
    "txCount": 74
  },
  {
    "date": "2021-06-12",
    "volume": 4688988.54,
    "txCount": 51
  },
  {
    "date": "2021-06-13",
    "volume": 5781942.74,
    "txCount": 53
  },
  {
    "date": "2021-06-14",
    "volume": 3828472.53,
    "txCount": 58
  },
  {
    "date": "2021-06-15",
    "volume": 1479978.9,
    "txCount": 37
  },
  {
    "date": "2021-06-16",
    "volume": 4112936.64,
    "txCount": 56
  },
  {
    "date": "2021-06-17",
    "volume": 5000577.34,
    "txCount": 31
  },
  {
    "date": "2021-06-18",
    "volume": 3714880.92,
    "txCount": 47
  },
  {
    "date": "2021-06-19",
    "volume": 15143094.02,
    "txCount": 93
  },
  {
    "date": "2021-06-20",
    "volume": 6678122.06,
    "txCount": 38
  },
  {
    "date": "2021-06-21",
    "volume": 20773070.73,
    "txCount": 42
  },
  {
    "date": "2021-06-22",
    "volume": 12189143.79,
    "txCount": 61
  },
  {
    "date": "2021-06-23",
    "volume": 1497439.16,
    "txCount": 40
  },
  {
    "date": "2021-06-24",
    "volume": 4024617.15,
    "txCount": 60
  },
  {
    "date": "2021-06-25",
    "volume": 13253546.56,
    "txCount": 59
  },
  {
    "date": "2021-06-26",
    "volume": 8168995.31,
    "txCount": 28
  },
  {
    "date": "2021-06-27",
    "volume": 4496220.57,
    "txCount": 37
  },
  {
    "date": "2021-06-28",
    "volume": 3139232.35,
    "txCount": 28
  },
  {
    "date": "2021-06-29",
    "volume": 18455914.07,
    "txCount": 51
  },
  {
    "date": "2021-06-30",
    "volume": 2597177.68,
    "txCount": 24
  },
  {
    "date": "2021-07-01",
    "volume": 2016720.19,
    "txCount": 29
  },
  {
    "date": "2021-07-02",
    "volume": 3948217.18,
    "txCount": 46
  },
  {
    "date": "2021-07-03",
    "volume": 1169810.12,
    "txCount": 31
  },
  {
    "date": "2021-07-04",
    "volume": 17624797.87,
    "txCount": 96
  },
  {
    "date": "2021-07-05",
    "volume": 4009195.35,
    "txCount": 82
  },
  {
    "date": "2021-07-06",
    "volume": 36402085.89,
    "txCount": 39
  },
  {
    "date": "2021-07-07",
    "volume": 3070738.04,
    "txCount": 24
  },
  {
    "date": "2021-07-08",
    "volume": 907410.47,
    "txCount": 29
  },
  {
    "date": "2021-07-09",
    "volume": 9961583.05,
    "txCount": 53
  },
  {
    "date": "2021-07-10",
    "volume": 1813285.94,
    "txCount": 28
  },
  {
    "date": "2021-07-11",
    "volume": 8703121,
    "txCount": 23
  },
  {
    "date": "2021-07-12",
    "volume": 5771463.34,
    "txCount": 31
  },
  {
    "date": "2021-07-13",
    "volume": 2335973.93,
    "txCount": 27
  },
  {
    "date": "2021-07-14",
    "volume": 2409451.78,
    "txCount": 39
  },
  {
    "date": "2021-07-15",
    "volume": 8079605.2,
    "txCount": 34
  },
  {
    "date": "2021-07-16",
    "volume": 12258858.66,
    "txCount": 26
  },
  {
    "date": "2021-07-17",
    "volume": 1609583.53,
    "txCount": 20
  },
  {
    "date": "2021-07-18",
    "volume": 2456196.33,
    "txCount": 15
  },
  {
    "date": "2021-07-19",
    "volume": 1591297.7,
    "txCount": 25
  },
  {
    "date": "2021-07-20",
    "volume": 7738636.69,
    "txCount": 25
  },
  {
    "date": "2021-07-21",
    "volume": 7088065.38,
    "txCount": 46
  },
  {
    "date": "2021-07-22",
    "volume": 6114639.99,
    "txCount": 22
  },
  {
    "date": "2021-07-23",
    "volume": 3348095.5,
    "txCount": 21
  },
  {
    "date": "2021-07-24",
    "volume": 17226815.01,
    "txCount": 30
  },
  {
    "date": "2021-07-25",
    "volume": 19235503.22,
    "txCount": 62
  },
  {
    "date": "2021-07-26",
    "volume": 4117694.2,
    "txCount": 57
  },
  {
    "date": "2021-07-27",
    "volume": 3052080.25,
    "txCount": 50
  },
  {
    "date": "2021-07-28",
    "volume": 5466735.96,
    "txCount": 59
  },
  {
    "date": "2021-07-29",
    "volume": 347591.32,
    "txCount": 45
  },
  {
    "date": "2021-07-30",
    "volume": 493198.19,
    "txCount": 33
  },
  {
    "date": "2021-07-31",
    "volume": 3837585.17,
    "txCount": 38
  },
  {
    "date": "2021-08-01",
    "volume": 3545548.44,
    "txCount": 29
  },
  {
    "date": "2021-08-02",
    "volume": 1779932.36,
    "txCount": 21
  },
  {
    "date": "2021-08-03",
    "volume": 653726.32,
    "txCount": 33
  },
  {
    "date": "2021-08-04",
    "volume": 149431.8,
    "txCount": 15
  },
  {
    "date": "2021-08-05",
    "volume": 203699.59,
    "txCount": 7
  },
  {
    "date": "2021-08-06",
    "volume": 1377920.65,
    "txCount": 22
  },
  {
    "date": "2021-08-07",
    "volume": 1702076.33,
    "txCount": 23
  },
  {
    "date": "2021-08-08",
    "volume": 3225846.07,
    "txCount": 19
  },
  {
    "date": "2021-08-09",
    "volume": 10431121.79,
    "txCount": 22
  },
  {
    "date": "2021-08-10",
    "volume": 2400571.19,
    "txCount": 20
  },
  {
    "date": "2021-08-11",
    "volume": 23294611.05,
    "txCount": 52
  },
  {
    "date": "2021-08-12",
    "volume": 4345743.94,
    "txCount": 20
  },
  {
    "date": "2021-08-13",
    "volume": 5213195.32,
    "txCount": 30
  },
  {
    "date": "2021-08-14",
    "volume": 2572645.99,
    "txCount": 32
  },
  {
    "date": "2021-08-15",
    "volume": 1320151.26,
    "txCount": 19
  },
  {
    "date": "2021-08-16",
    "volume": 3261329.34,
    "txCount": 36
  },
  {
    "date": "2021-08-17",
    "volume": 4396416.97,
    "txCount": 36
  },
  {
    "date": "2021-08-18",
    "volume": 489055.69,
    "txCount": 13
  },
  {
    "date": "2021-08-19",
    "volume": 3964409.98,
    "txCount": 37
  },
  {
    "date": "2021-08-20",
    "volume": 5796493.31,
    "txCount": 45
  },
  {
    "date": "2021-08-21",
    "volume": 3230335.99,
    "txCount": 25
  },
  {
    "date": "2021-08-22",
    "volume": 644370.27,
    "txCount": 8
  },
  {
    "date": "2021-08-23",
    "volume": 8330619.57,
    "txCount": 18
  },
  {
    "date": "2021-08-24",
    "volume": 354608.93,
    "txCount": 12
  },
  {
    "date": "2021-08-25",
    "volume": 1597844.85,
    "txCount": 16
  },
  {
    "date": "2021-08-26",
    "volume": 1432625.97,
    "txCount": 10
  },
  {
    "date": "2021-08-27",
    "volume": 1607625.93,
    "txCount": 18
  },
  {
    "date": "2021-08-28",
    "volume": 1579893.64,
    "txCount": 20
  },
  {
    "date": "2021-08-29",
    "volume": 4664987.32,
    "txCount": 12
  },
  {
    "date": "2021-08-30",
    "volume": 1289573.51,
    "txCount": 14
  },
  {
    "date": "2021-08-31",
    "volume": 1198109.68,
    "txCount": 10
  },
  {
    "date": "2021-09-01",
    "volume": 13535302.37,
    "txCount": 19
  },
  {
    "date": "2021-09-02",
    "volume": 1482849.69,
    "txCount": 11
  },
  {
    "date": "2021-09-03",
    "volume": 4815692.59,
    "txCount": 22
  },
  {
    "date": "2021-09-04",
    "volume": 8481259.84,
    "txCount": 16
  },
  {
    "date": "2021-09-05",
    "volume": 1606706.58,
    "txCount": 14
  },
  {
    "date": "2021-09-06",
    "volume": 1572814.93,
    "txCount": 11
  },
  {
    "date": "2021-09-07",
    "volume": 1419476.97,
    "txCount": 13
  },
  {
    "date": "2021-09-08",
    "volume": 2473025.27,
    "txCount": 6
  },
  {
    "date": "2021-09-09",
    "volume": 6983864.16,
    "txCount": 20
  },
  {
    "date": "2021-09-10",
    "volume": 4682613.13,
    "txCount": 6
  },
  {
    "date": "2021-09-11",
    "volume": 1365458.85,
    "txCount": 20
  },
  {
    "date": "2021-09-12",
    "volume": 1908327.29,
    "txCount": 11
  },
  {
    "date": "2021-09-13",
    "volume": 2546026.76,
    "txCount": 9
  },
  {
    "date": "2021-09-14",
    "volume": 4200771.34,
    "txCount": 11
  },
  {
    "date": "2021-09-15",
    "volume": 1358755.02,
    "txCount": 9
  },
  {
    "date": "2021-09-16",
    "volume": 1172122.26,
    "txCount": 8
  },
  {
    "date": "2021-09-17",
    "volume": 2174646.14,
    "txCount": 13
  },
  {
    "date": "2021-09-18",
    "volume": 6667400.58,
    "txCount": 17
  },
  {
    "date": "2021-09-19",
    "volume": 4196776.2,
    "txCount": 8
  },
  {
    "date": "2021-09-20",
    "volume": 3379437.61,
    "txCount": 16
  },
  {
    "date": "2021-09-21",
    "volume": 2592586.64,
    "txCount": 12
  },
  {
    "date": "2021-09-22",
    "volume": 884414.62,
    "txCount": 3
  },
  {
    "date": "2021-09-23",
    "volume": 882432.5,
    "txCount": 4
  },
  {
    "date": "2021-09-24",
    "volume": 347788.62,
    "txCount": 8
  },
  {
    "date": "2021-09-25",
    "volume": 73513.91,
    "txCount": 5
  },
  {
    "date": "2021-09-26",
    "volume": 590241.82,
    "txCount": 8
  },
  {
    "date": "2021-09-27",
    "volume": 739934.57,
    "txCount": 7
  },
  {
    "date": "2021-09-28",
    "volume": 9246935.17,
    "txCount": 6
  },
  {
    "date": "2021-09-29",
    "volume": 3282080.29,
    "txCount": 7
  },
  {
    "date": "2021-09-30",
    "volume": 2002087.44,
    "txCount": 8
  },
  {
    "date": "2021-10-01",
    "volume": 455569.71,
    "txCount": 8
  },
  {
    "date": "2021-10-02",
    "volume": 4416810.09,
    "txCount": 9
  },
  {
    "date": "2021-10-03",
    "volume": 75172.03,
    "txCount": 8
  },
  {
    "date": "2021-10-04",
    "volume": 120867.92,
    "txCount": 3
  },
  {
    "date": "2021-10-05",
    "volume": 3380468.63,
    "txCount": 5
  },
  {
    "date": "2021-10-06",
    "volume": 1471321.74,
    "txCount": 8
  },
  {
    "date": "2021-10-07",
    "volume": 2482707.19,
    "txCount": 11
  },
  {
    "date": "2021-10-08",
    "volume": 16750830.27,
    "txCount": 16
  },
  {
    "date": "2021-10-09",
    "volume": 7939107.8,
    "txCount": 22
  },
  {
    "date": "2021-10-10",
    "volume": 1323987.42,
    "txCount": 14
  },
  {
    "date": "2021-10-11",
    "volume": 1113045.04,
    "txCount": 16
  },
  {
    "date": "2021-10-12",
    "volume": 971856.68,
    "txCount": 10
  },
  {
    "date": "2021-10-13",
    "volume": 1640738.76,
    "txCount": 9
  },
  {
    "date": "2021-10-14",
    "volume": 4096572.1,
    "txCount": 13
  },
  {
    "date": "2021-10-15",
    "volume": 1726705.61,
    "txCount": 16
  },
  {
    "date": "2021-10-16",
    "volume": 1420419.19,
    "txCount": 14
  },
  {
    "date": "2021-10-17",
    "volume": 864301.96,
    "txCount": 14
  },
  {
    "date": "2021-10-18",
    "volume": 391595.42,
    "txCount": 12
  },
  {
    "date": "2021-10-19",
    "volume": 7133304.24,
    "txCount": 18
  },
  {
    "date": "2021-10-20",
    "volume": 2794677.99,
    "txCount": 15
  },
  {
    "date": "2021-10-21",
    "volume": 651398.27,
    "txCount": 12
  },
  {
    "date": "2021-10-22",
    "volume": 833404.38,
    "txCount": 11
  },
  {
    "date": "2021-10-23",
    "volume": 7494293.5,
    "txCount": 16
  },
  {
    "date": "2021-10-24",
    "volume": 5343118.88,
    "txCount": 23
  },
  {
    "date": "2021-10-25",
    "volume": 2053507.31,
    "txCount": 20
  },
  {
    "date": "2021-10-26",
    "volume": 11622925.13,
    "txCount": 42
  },
  {
    "date": "2021-10-27",
    "volume": 10290428.83,
    "txCount": 38
  },
  {
    "date": "2021-10-28",
    "volume": 23305301.85,
    "txCount": 105
  },
  {
    "date": "2021-10-29",
    "volume": 35250742.21,
    "txCount": 116
  },
  {
    "date": "2021-10-30",
    "volume": 4289522.71,
    "txCount": 72
  },
  {
    "date": "2021-10-31",
    "volume": 20329790.41,
    "txCount": 88
  },
  {
    "date": "2021-11-01",
    "volume": 14668040.6,
    "txCount": 128
  },
  {
    "date": "2021-11-02",
    "volume": 6670147.09,
    "txCount": 113
  },
  {
    "date": "2021-11-03",
    "volume": 3547373.15,
    "txCount": 87
  },
  {
    "date": "2021-11-04",
    "volume": 16983067,
    "txCount": 167
  },
  {
    "date": "2021-11-05",
    "volume": 7883335.89,
    "txCount": 139
  },
  {
    "date": "2021-11-06",
    "volume": 6458457.54,
    "txCount": 197
  },
  {
    "date": "2021-11-07",
    "volume": 13473311.25,
    "txCount": 238
  },
  {
    "date": "2021-11-08",
    "volume": 16373049.39,
    "txCount": 191
  },
  {
    "date": "2021-11-09",
    "volume": 35956886.62,
    "txCount": 486
  },
  {
    "date": "2021-11-10",
    "volume": 93713141.84,
    "txCount": 3331
  },
  {
    "date": "2021-11-11",
    "volume": 67938613.9,
    "txCount": 2709
  },
  {
    "date": "2021-11-12",
    "volume": 15043274.52,
    "txCount": 660
  },
  {
    "date": "2021-11-13",
    "volume": 7409200.6,
    "txCount": 416
  },
  {
    "date": "2021-11-14",
    "volume": 12249189.01,
    "txCount": 469
  },
  {
    "date": "2021-11-15",
    "volume": 9702534.02,
    "txCount": 317
  },
  {
    "date": "2021-11-16",
    "volume": 12279808.46,
    "txCount": 262
  },
  {
    "date": "2021-11-17",
    "volume": 9541657.74,
    "txCount": 300
  },
  {
    "date": "2021-11-18",
    "volume": 4936029.6,
    "txCount": 205
  },
  {
    "date": "2021-11-19",
    "volume": 9053382.67,
    "txCount": 219
  },
  {
    "date": "2021-11-20",
    "volume": 7928162,
    "txCount": 297
  },
  {
    "date": "2021-11-21",
    "volume": 14172927.69,
    "txCount": 214
  },
  {
    "date": "2021-11-22",
    "volume": 5288866.96,
    "txCount": 214
  },
  {
    "date": "2021-11-23",
    "volume": 4213798.25,
    "txCount": 219
  },
  {
    "date": "2021-11-24",
    "volume": 9582259.62,
    "txCount": 199
  },
  {
    "date": "2021-11-25",
    "volume": 7191506.88,
    "txCount": 270
  },
  {
    "date": "2021-11-26",
    "volume": 13224065.11,
    "txCount": 247
  },
  {
    "date": "2021-11-27",
    "volume": 5383156.49,
    "txCount": 139
  },
  {
    "date": "2021-11-28",
    "volume": 3974805.72,
    "txCount": 113
  },
  {
    "date": "2021-11-29",
    "volume": 6038680.45,
    "txCount": 130
  },
  {
    "date": "2021-11-30",
    "volume": 3488523.13,
    "txCount": 108
  },
  {
    "date": "2021-12-01",
    "volume": 9039395.68,
    "txCount": 100
  },
  {
    "date": "2021-12-02",
    "volume": 14679072.08,
    "txCount": 151
  },
  {
    "date": "2021-12-03",
    "volume": 4820559.37,
    "txCount": 77
  },
  {
    "date": "2021-12-04",
    "volume": 16849143.17,
    "txCount": 84
  },
  {
    "date": "2021-12-05",
    "volume": 11235946.46,
    "txCount": 74
  },
  {
    "date": "2021-12-06",
    "volume": 8347610.01,
    "txCount": 49
  },
  {
    "date": "2021-12-07",
    "volume": 2312705.68,
    "txCount": 69
  },
  {
    "date": "2021-12-08",
    "volume": 2476947.7,
    "txCount": 46
  },
  {
    "date": "2021-12-09",
    "volume": 4146957.91,
    "txCount": 49
  },
  {
    "date": "2021-12-10",
    "volume": 4035917.8,
    "txCount": 47
  },
  {
    "date": "2021-12-11",
    "volume": 4813552.33,
    "txCount": 51
  },
  {
    "date": "2021-12-12",
    "volume": 3662964.03,
    "txCount": 41
  },
  {
    "date": "2021-12-13",
    "volume": 488695.43,
    "txCount": 23
  },
  {
    "date": "2021-12-14",
    "volume": 307460.73,
    "txCount": 25
  },
  {
    "date": "2021-12-15",
    "volume": 2453325.06,
    "txCount": 35
  },
  {
    "date": "2021-12-16",
    "volume": 3585664.48,
    "txCount": 40
  },
  {
    "date": "2021-12-17",
    "volume": 1154566.97,
    "txCount": 29
  },
  {
    "date": "2021-12-18",
    "volume": 2534521.16,
    "txCount": 26
  },
  {
    "date": "2021-12-19",
    "volume": 1459913.22,
    "txCount": 30
  },
  {
    "date": "2021-12-20",
    "volume": 2556578.54,
    "txCount": 27
  },
  {
    "date": "2021-12-21",
    "volume": 407745.07,
    "txCount": 20
  },
  {
    "date": "2021-12-22",
    "volume": 1859143.02,
    "txCount": 31
  },
  {
    "date": "2021-12-23",
    "volume": 2223686.34,
    "txCount": 26
  },
  {
    "date": "2021-12-24",
    "volume": 485332.26,
    "txCount": 24
  },
  {
    "date": "2021-12-25",
    "volume": 902739.56,
    "txCount": 16
  },
  {
    "date": "2021-12-26",
    "volume": 2998893.32,
    "txCount": 26
  },
  {
    "date": "2021-12-27",
    "volume": 2973026.31,
    "txCount": 33
  },
  {
    "date": "2021-12-28",
    "volume": 1571861.15,
    "txCount": 34
  },
  {
    "date": "2021-12-29",
    "volume": 1254280.39,
    "txCount": 31
  },
  {
    "date": "2021-12-30",
    "volume": 1888951.02,
    "txCount": 32
  },
  {
    "date": "2021-12-31",
    "volume": 3933809.4,
    "txCount": 27
  },
  {
    "date": "2022-01-01",
    "volume": 323886.62,
    "txCount": 17
  },
  {
    "date": "2022-01-02",
    "volume": 451502.29,
    "txCount": 18
  },
  {
    "date": "2022-01-03",
    "volume": 3858296.74,
    "txCount": 32
  },
  {
    "date": "2022-01-04",
    "volume": 775390.53,
    "txCount": 24
  },
  {
    "date": "2022-01-05",
    "volume": 1380208.61,
    "txCount": 31
  },
  {
    "date": "2022-01-06",
    "volume": 613426.43,
    "txCount": 16
  },
  {
    "date": "2022-01-07",
    "volume": 4366167.64,
    "txCount": 20
  },
  {
    "date": "2022-01-08",
    "volume": 5754048.51,
    "txCount": 27
  },
  {
    "date": "2022-01-09",
    "volume": 1015095.08,
    "txCount": 29
  },
  {
    "date": "2022-01-10",
    "volume": 1537143.91,
    "txCount": 26
  },
  {
    "date": "2022-01-11",
    "volume": 1047091.26,
    "txCount": 23
  },
  {
    "date": "2022-01-12",
    "volume": 2852684.31,
    "txCount": 34
  },
  {
    "date": "2022-01-13",
    "volume": 486447.95,
    "txCount": 16
  },
  {
    "date": "2022-01-14",
    "volume": 310532.03,
    "txCount": 22
  },
  {
    "date": "2022-01-15",
    "volume": 5781167.25,
    "txCount": 27
  },
  {
    "date": "2022-01-16",
    "volume": 347088.14,
    "txCount": 10
  },
  {
    "date": "2022-01-17",
    "volume": 4649147.8,
    "txCount": 14
  },
  {
    "date": "2022-01-18",
    "volume": 492094.06,
    "txCount": 16
  },
  {
    "date": "2022-01-19",
    "volume": 85000.79,
    "txCount": 13
  },
  {
    "date": "2022-01-20",
    "volume": 230183.57,
    "txCount": 12
  },
  {
    "date": "2022-01-21",
    "volume": 690338.71,
    "txCount": 15
  },
  {
    "date": "2022-01-22",
    "volume": 5931669.1,
    "txCount": 33
  },
  {
    "date": "2022-01-23",
    "volume": 2770448.8,
    "txCount": 28
  },
  {
    "date": "2022-01-24",
    "volume": 2020147.6,
    "txCount": 26
  },
  {
    "date": "2022-01-25",
    "volume": 7373423.6,
    "txCount": 24
  },
  {
    "date": "2022-01-26",
    "volume": 2310130.57,
    "txCount": 25
  },
  {
    "date": "2022-01-27",
    "volume": 730673.3,
    "txCount": 12
  },
  {
    "date": "2022-01-28",
    "volume": 685794.58,
    "txCount": 10
  },
  {
    "date": "2022-01-29",
    "volume": 366435.99,
    "txCount": 22
  },
  {
    "date": "2022-01-30",
    "volume": 60351.88,
    "txCount": 8
  },
  {
    "date": "2022-01-31",
    "volume": 1427213.15,
    "txCount": 23
  },
  {
    "date": "2022-02-01",
    "volume": 3494068.99,
    "txCount": 26
  },
  {
    "date": "2022-02-02",
    "volume": 567987.41,
    "txCount": 31
  },
  {
    "date": "2022-02-03",
    "volume": 311030.82,
    "txCount": 13
  },
  {
    "date": "2022-02-04",
    "volume": 2065517.79,
    "txCount": 22
  },
  {
    "date": "2022-02-05",
    "volume": 642131.53,
    "txCount": 19
  },
  {
    "date": "2022-02-06",
    "volume": 525841.42,
    "txCount": 62
  },
  {
    "date": "2022-02-07",
    "volume": 2974037.24,
    "txCount": 33
  },
  {
    "date": "2022-02-08",
    "volume": 6194884.95,
    "txCount": 17
  },
  {
    "date": "2022-02-09",
    "volume": 3403336.86,
    "txCount": 5
  },
  {
    "date": "2022-02-10",
    "volume": 284102.17,
    "txCount": 4
  },
  {
    "date": "2022-02-11",
    "volume": 8610566.84,
    "txCount": 10
  },
  {
    "date": "2022-02-12",
    "volume": 1086804.4,
    "txCount": 14
  },
  {
    "date": "2022-02-13",
    "volume": 627819.41,
    "txCount": 8
  },
  {
    "date": "2022-02-14",
    "volume": 425044.28,
    "txCount": 6
  },
  {
    "date": "2022-02-15",
    "volume": 4528512.35,
    "txCount": 22
  },
  {
    "date": "2022-02-16",
    "volume": 281223.46,
    "txCount": 7
  },
  {
    "date": "2022-02-17",
    "volume": 3304012.24,
    "txCount": 8
  },
  {
    "date": "2022-02-18",
    "volume": 712442.48,
    "txCount": 11
  },
  {
    "date": "2022-02-19",
    "volume": 339995.28,
    "txCount": 8
  },
  {
    "date": "2022-02-20",
    "volume": 1410424.73,
    "txCount": 9
  },
  {
    "date": "2022-02-21",
    "volume": 473796.8,
    "txCount": 7
  },
  {
    "date": "2022-02-22",
    "volume": 332751.26,
    "txCount": 5
  },
  {
    "date": "2022-02-23",
    "volume": 296075.92,
    "txCount": 6
  },
  {
    "date": "2022-02-24",
    "volume": 1117443.52,
    "txCount": 11
  },
  {
    "date": "2022-02-25",
    "volume": 4216.57,
    "txCount": 2
  },
  {
    "date": "2022-02-26",
    "volume": 3333174.89,
    "txCount": 9
  },
  {
    "date": "2022-02-27",
    "volume": 3484138.17,
    "txCount": 4
  },
  {
    "date": "2022-02-28",
    "volume": 1224614.62,
    "txCount": 7
  },
  {
    "date": "2022-03-01",
    "volume": 326972.27,
    "txCount": 8
  },
  {
    "date": "2022-03-02",
    "volume": 2471607.02,
    "txCount": 9
  },
  {
    "date": "2022-03-03",
    "volume": 867213.68,
    "txCount": 7
  },
  {
    "date": "2022-03-04",
    "volume": 5502022.61,
    "txCount": 10
  },
  {
    "date": "2022-03-05",
    "volume": 355935.21,
    "txCount": 7
  },
  {
    "date": "2022-03-07",
    "volume": 17644.07,
    "txCount": 3
  },
  {
    "date": "2022-03-08",
    "volume": 217579.88,
    "txCount": 5
  },
  {
    "date": "2022-03-09",
    "volume": 77896.47,
    "txCount": 7
  },
  {
    "date": "2022-03-10",
    "volume": 187018.6,
    "txCount": 1
  },
  {
    "date": "2022-03-11",
    "volume": 1429888.64,
    "txCount": 2
  },
  {
    "date": "2022-03-12",
    "volume": 2203332.59,
    "txCount": 13
  },
  {
    "date": "2022-03-13",
    "volume": 3860547.38,
    "txCount": 10
  },
  {
    "date": "2022-03-14",
    "volume": 2085106.62,
    "txCount": 7
  },
  {
    "date": "2022-03-15",
    "volume": 142510.29,
    "txCount": 5
  },
  {
    "date": "2022-03-16",
    "volume": 351646.57,
    "txCount": 6
  },
  {
    "date": "2022-03-17",
    "volume": 525715.08,
    "txCount": 6
  },
  {
    "date": "2022-03-18",
    "volume": 4192386.03,
    "txCount": 10
  },
  {
    "date": "2022-03-19",
    "volume": 2783974.14,
    "txCount": 11
  },
  {
    "date": "2022-03-20",
    "volume": 2921881.71,
    "txCount": 4
  },
  {
    "date": "2022-03-21",
    "volume": 573160.71,
    "txCount": 5
  },
  {
    "date": "2022-03-22",
    "volume": 2852126.05,
    "txCount": 14
  },
  {
    "date": "2022-03-23",
    "volume": 931871.01,
    "txCount": 12
  },
  {
    "date": "2022-03-24",
    "volume": 87768.02,
    "txCount": 3
  },
  {
    "date": "2022-03-25",
    "volume": 1236085.86,
    "txCount": 12
  },
  {
    "date": "2022-03-27",
    "volume": 45337.14,
    "txCount": 6
  },
  {
    "date": "2022-03-28",
    "volume": 642199.54,
    "txCount": 9
  },
  {
    "date": "2022-03-29",
    "volume": 373085.15,
    "txCount": 8
  },
  {
    "date": "2022-03-30",
    "volume": 74776.3,
    "txCount": 7
  },
  {
    "date": "2022-03-31",
    "volume": 224430.9,
    "txCount": 8
  },
  {
    "date": "2022-04-01",
    "volume": 268012.11,
    "txCount": 10
  },
  {
    "date": "2022-04-02",
    "volume": 20847.67,
    "txCount": 1
  },
  {
    "date": "2022-04-03",
    "volume": 241932.25,
    "txCount": 6
  },
  {
    "date": "2022-04-04",
    "volume": 70390.08,
    "txCount": 7
  },
  {
    "date": "2022-04-05",
    "volume": 227912.91,
    "txCount": 10
  },
  {
    "date": "2022-04-06",
    "volume": 18990.61,
    "txCount": 4
  },
  {
    "date": "2022-04-07",
    "volume": 499857.12,
    "txCount": 7
  },
  {
    "date": "2022-04-08",
    "volume": 65270.71,
    "txCount": 2
  },
  {
    "date": "2022-04-09",
    "volume": 2639318.96,
    "txCount": 7
  },
  {
    "date": "2022-04-10",
    "volume": 72825.29,
    "txCount": 4
  },
  {
    "date": "2022-04-11",
    "volume": 168033.46,
    "txCount": 2
  },
  {
    "date": "2022-04-12",
    "volume": 130223.96,
    "txCount": 4
  },
  {
    "date": "2022-04-13",
    "volume": 366239.65,
    "txCount": 3
  },
  {
    "date": "2022-04-14",
    "volume": 597317.21,
    "txCount": 4
  },
  {
    "date": "2022-04-15",
    "volume": 326196.71,
    "txCount": 6
  },
  {
    "date": "2022-04-16",
    "volume": 1165745.09,
    "txCount": 3
  },
  {
    "date": "2022-04-17",
    "volume": 1411350.97,
    "txCount": 4
  },
  {
    "date": "2022-04-18",
    "volume": 1395902.45,
    "txCount": 4
  },
  {
    "date": "2022-04-19",
    "volume": 679976.31,
    "txCount": 4
  },
  {
    "date": "2022-04-20",
    "volume": 250757.5,
    "txCount": 4
  },
  {
    "date": "2022-04-21",
    "volume": 3679.71,
    "txCount": 1
  },
  {
    "date": "2022-04-22",
    "volume": 155904.38,
    "txCount": 3
  },
  {
    "date": "2022-04-23",
    "volume": 1866238.84,
    "txCount": 13
  },
  {
    "date": "2022-04-24",
    "volume": 243755.57,
    "txCount": 6
  },
  {
    "date": "2022-04-25",
    "volume": 3655886.62,
    "txCount": 11
  },
  {
    "date": "2022-04-26",
    "volume": 80528.83,
    "txCount": 2
  },
  {
    "date": "2022-04-27",
    "volume": 195327.24,
    "txCount": 5
  },
  {
    "date": "2022-04-28",
    "volume": 246755.71,
    "txCount": 10
  },
  {
    "date": "2022-04-29",
    "volume": 1195348.36,
    "txCount": 5
  },
  {
    "date": "2022-04-30",
    "volume": 1724129.48,
    "txCount": 3
  },
  {
    "date": "2022-05-01",
    "volume": 51974.97,
    "txCount": 3
  },
  {
    "date": "2022-05-02",
    "volume": 34165.44,
    "txCount": 4
  },
  {
    "date": "2022-05-03",
    "volume": 1395777.27,
    "txCount": 6
  },
  {
    "date": "2022-05-04",
    "volume": 734580.15,
    "txCount": 4
  },
  {
    "date": "2022-05-05",
    "volume": 11977.55,
    "txCount": 1
  },
  {
    "date": "2022-05-06",
    "volume": 12447.82,
    "txCount": 3
  },
  {
    "date": "2022-05-07",
    "volume": 45702.58,
    "txCount": 3
  },
  {
    "date": "2022-05-08",
    "volume": 2836180.73,
    "txCount": 9
  },
  {
    "date": "2022-05-09",
    "volume": 852399.21,
    "txCount": 5
  },
  {
    "date": "2022-05-10",
    "volume": 3415844.59,
    "txCount": 2
  },
  {
    "date": "2022-05-11",
    "volume": 13578473.82,
    "txCount": 12
  },
  {
    "date": "2022-05-12",
    "volume": 30480158.43,
    "txCount": 33
  },
  {
    "date": "2022-05-13",
    "volume": 3986634.61,
    "txCount": 21
  },
  {
    "date": "2022-05-14",
    "volume": 3759801.81,
    "txCount": 8
  },
  {
    "date": "2022-05-15",
    "volume": 2120426.83,
    "txCount": 2
  },
  {
    "date": "2022-05-16",
    "volume": 347944.9,
    "txCount": 4
  },
  {
    "date": "2022-05-17",
    "volume": 15682386.61,
    "txCount": 9
  },
  {
    "date": "2022-05-18",
    "volume": 28491.25,
    "txCount": 1
  },
  {
    "date": "2022-05-20",
    "volume": 254571.24,
    "txCount": 5
  },
  {
    "date": "2022-05-21",
    "volume": 2588779.55,
    "txCount": 8
  },
  {
    "date": "2022-05-22",
    "volume": 5197.82,
    "txCount": 2
  },
  {
    "date": "2022-05-23",
    "volume": 62252.8,
    "txCount": 2
  },
  {
    "date": "2022-05-24",
    "volume": 111570.12,
    "txCount": 2
  },
  {
    "date": "2022-05-25",
    "volume": 18800,
    "txCount": 2
  },
  {
    "date": "2022-05-26",
    "volume": 415957.9,
    "txCount": 4
  },
  {
    "date": "2022-05-27",
    "volume": 268052.7,
    "txCount": 3
  },
  {
    "date": "2022-05-28",
    "volume": 27669.87,
    "txCount": 2
  },
  {
    "date": "2022-05-29",
    "volume": 5800.06,
    "txCount": 2
  },
  {
    "date": "2022-05-30",
    "volume": 24300.84,
    "txCount": 1
  },
  {
    "date": "2022-05-31",
    "volume": 998.09,
    "txCount": 3
  },
  {
    "date": "2022-06-01",
    "volume": 291400,
    "txCount": 3
  },
  {
    "date": "2022-06-02",
    "volume": 17672.44,
    "txCount": 1
  },
  {
    "date": "2022-06-05",
    "volume": 9688.52,
    "txCount": 1
  },
  {
    "date": "2022-06-06",
    "volume": 4558765.91,
    "txCount": 4
  },
  {
    "date": "2022-06-09",
    "volume": 2279273.74,
    "txCount": 3
  },
  {
    "date": "2022-06-10",
    "volume": 302361.38,
    "txCount": 7
  },
  {
    "date": "2022-06-11",
    "volume": 27488.98,
    "txCount": 2
  },
  {
    "date": "2022-06-12",
    "volume": 62609.69,
    "txCount": 3
  },
  {
    "date": "2022-06-13",
    "volume": 473021.01,
    "txCount": 5
  },
  {
    "date": "2022-06-14",
    "volume": 2739902.83,
    "txCount": 4
  },
  {
    "date": "2022-06-15",
    "volume": 37600.94,
    "txCount": 1
  },
  {
    "date": "2022-06-16",
    "volume": 596251.41,
    "txCount": 5
  },
  {
    "date": "2022-06-17",
    "volume": 75555.37,
    "txCount": 7
  },
  {
    "date": "2022-06-19",
    "volume": 282868.8,
    "txCount": 2
  },
  {
    "date": "2022-06-20",
    "volume": 38383.07,
    "txCount": 1
  },
  {
    "date": "2022-06-22",
    "volume": 1644699.88,
    "txCount": 9
  },
  {
    "date": "2022-06-23",
    "volume": 77470.66,
    "txCount": 4
  },
  {
    "date": "2022-06-24",
    "volume": 628597.66,
    "txCount": 3
  },
  {
    "date": "2022-06-27",
    "volume": 1291186.32,
    "txCount": 3
  },
  {
    "date": "2022-06-28",
    "volume": 260952.38,
    "txCount": 3
  },
  {
    "date": "2022-06-29",
    "volume": 253998.09,
    "txCount": 6
  },
  {
    "date": "2022-06-30",
    "volume": 1453814.48,
    "txCount": 8
  },
  {
    "date": "2022-07-02",
    "volume": 1609111.45,
    "txCount": 4
  },
  {
    "date": "2022-07-03",
    "volume": 1831109.6,
    "txCount": 2
  },
  {
    "date": "2022-07-04",
    "volume": 682050.74,
    "txCount": 12
  },
  {
    "date": "2022-07-05",
    "volume": 7524.67,
    "txCount": 2
  },
  {
    "date": "2022-07-06",
    "volume": 368.32,
    "txCount": 1
  },
  {
    "date": "2022-07-08",
    "volume": 2838.8,
    "txCount": 1
  },
  {
    "date": "2022-07-10",
    "volume": 7624.34,
    "txCount": 2
  },
  {
    "date": "2022-07-11",
    "volume": 1732690.96,
    "txCount": 12
  },
  {
    "date": "2022-07-12",
    "volume": 777898.72,
    "txCount": 6
  },
  {
    "date": "2022-07-13",
    "volume": 2526193.94,
    "txCount": 7
  },
  {
    "date": "2022-07-14",
    "volume": 2836134.44,
    "txCount": 11
  },
  {
    "date": "2022-07-15",
    "volume": 3420517.61,
    "txCount": 12
  },
  {
    "date": "2022-07-16",
    "volume": 1148948.78,
    "txCount": 7
  },
  {
    "date": "2022-07-17",
    "volume": 272657.2,
    "txCount": 3
  },
  {
    "date": "2022-07-18",
    "volume": 480340.37,
    "txCount": 5
  },
  {
    "date": "2022-07-19",
    "volume": 823656.81,
    "txCount": 11
  },
  {
    "date": "2022-07-20",
    "volume": 730744.09,
    "txCount": 3
  },
  {
    "date": "2022-07-21",
    "volume": 409494.78,
    "txCount": 4
  },
  {
    "date": "2022-07-22",
    "volume": 3022200.98,
    "txCount": 7
  },
  {
    "date": "2022-07-23",
    "volume": 10676810.81,
    "txCount": 14
  },
  {
    "date": "2022-07-24",
    "volume": 1317421.66,
    "txCount": 2
  },
  {
    "date": "2022-07-25",
    "volume": 475870.84,
    "txCount": 5
  },
  {
    "date": "2022-07-26",
    "volume": 30628.19,
    "txCount": 2
  },
  {
    "date": "2022-07-27",
    "volume": 78444.54,
    "txCount": 3
  },
  {
    "date": "2022-07-28",
    "volume": 108120,
    "txCount": 2
  },
  {
    "date": "2022-07-29",
    "volume": 467450.76,
    "txCount": 2
  },
  {
    "date": "2022-07-30",
    "volume": 914216.45,
    "txCount": 7
  },
  {
    "date": "2022-07-31",
    "volume": 5039701.18,
    "txCount": 5
  },
  {
    "date": "2022-08-01",
    "volume": 4714100,
    "txCount": 2
  },
  {
    "date": "2022-08-02",
    "volume": 151993.15,
    "txCount": 2
  },
  {
    "date": "2022-08-03",
    "volume": 8523.33,
    "txCount": 3
  },
  {
    "date": "2022-08-04",
    "volume": 98715.51,
    "txCount": 2
  },
  {
    "date": "2022-08-05",
    "volume": 406876.88,
    "txCount": 3
  },
  {
    "date": "2022-08-06",
    "volume": 776533.99,
    "txCount": 6
  },
  {
    "date": "2022-08-07",
    "volume": 99267.69,
    "txCount": 2
  },
  {
    "date": "2022-08-08",
    "volume": 55660.97,
    "txCount": 1
  },
  {
    "date": "2022-08-09",
    "volume": 105674.34,
    "txCount": 7
  },
  {
    "date": "2022-08-10",
    "volume": 46798.26,
    "txCount": 2
  },
  {
    "date": "2022-08-11",
    "volume": 133844.87,
    "txCount": 3
  },
  {
    "date": "2022-08-13",
    "volume": 617749.91,
    "txCount": 3
  },
  {
    "date": "2022-08-14",
    "volume": 369008.15,
    "txCount": 4
  },
  {
    "date": "2022-08-15",
    "volume": 20712401.04,
    "txCount": 10
  },
  {
    "date": "2022-08-16",
    "volume": 1688588.58,
    "txCount": 10
  },
  {
    "date": "2022-08-17",
    "volume": 344877.54,
    "txCount": 2
  },
  {
    "date": "2022-08-18",
    "volume": 13540.75,
    "txCount": 1
  },
  {
    "date": "2022-08-20",
    "volume": 86468.38,
    "txCount": 4
  },
  {
    "date": "2022-08-21",
    "volume": 619696.33,
    "txCount": 2
  },
  {
    "date": "2022-08-22",
    "volume": 940000,
    "txCount": 1
  },
  {
    "date": "2022-08-23",
    "volume": 957914.48,
    "txCount": 3
  },
  {
    "date": "2022-08-24",
    "volume": 475340.2,
    "txCount": 3
  },
  {
    "date": "2022-08-25",
    "volume": 2563236.77,
    "txCount": 10
  },
  {
    "date": "2022-08-27",
    "volume": 895988.09,
    "txCount": 2
  },
  {
    "date": "2022-08-28",
    "volume": 896448.37,
    "txCount": 2
  },
  {
    "date": "2022-08-29",
    "volume": 564000,
    "txCount": 1
  },
  {
    "date": "2022-08-30",
    "volume": 2005377.78,
    "txCount": 3
  },
  {
    "date": "2022-09-01",
    "volume": 476079.33,
    "txCount": 6
  },
  {
    "date": "2022-09-02",
    "volume": 36101.59,
    "txCount": 1
  },
  {
    "date": "2022-09-04",
    "volume": 95740.33,
    "txCount": 3
  },
  {
    "date": "2022-09-05",
    "volume": 1881044.34,
    "txCount": 2
  },
  {
    "date": "2022-09-06",
    "volume": 2035147.87,
    "txCount": 4
  },
  {
    "date": "2022-09-08",
    "volume": 184697.47,
    "txCount": 2
  },
  {
    "date": "2022-09-09",
    "volume": 92533.64,
    "txCount": 3
  },
  {
    "date": "2022-09-10",
    "volume": 2077853.64,
    "txCount": 4
  },
  {
    "date": "2022-09-11",
    "volume": 4958505.87,
    "txCount": 7
  },
  {
    "date": "2022-09-12",
    "volume": 277255.45,
    "txCount": 2
  },
  {
    "date": "2022-09-13",
    "volume": 9856257.51,
    "txCount": 7
  },
  {
    "date": "2022-09-14",
    "volume": 784762.15,
    "txCount": 3
  },
  {
    "date": "2022-09-15",
    "volume": 1769.51,
    "txCount": 1
  },
  {
    "date": "2022-09-16",
    "volume": 50139.9,
    "txCount": 1
  },
  {
    "date": "2022-09-17",
    "volume": 557863.75,
    "txCount": 3
  },
  {
    "date": "2022-09-18",
    "volume": 2640.48,
    "txCount": 1
  },
  {
    "date": "2022-09-19",
    "volume": 1288416.67,
    "txCount": 3
  },
  {
    "date": "2022-09-20",
    "volume": 20.86,
    "txCount": 1
  },
  {
    "date": "2022-09-21",
    "volume": 3177.2,
    "txCount": 2
  },
  {
    "date": "2022-09-22",
    "volume": 1001977.14,
    "txCount": 6
  },
  {
    "date": "2022-09-23",
    "volume": 51318.66,
    "txCount": 1
  },
  {
    "date": "2022-09-24",
    "volume": 298256.44,
    "txCount": 1
  },
  {
    "date": "2022-09-25",
    "volume": 174208.98,
    "txCount": 2
  },
  {
    "date": "2022-09-28",
    "volume": 175048.07,
    "txCount": 2
  },
  {
    "date": "2022-09-29",
    "volume": 9938.91,
    "txCount": 1
  },
  {
    "date": "2022-09-30",
    "volume": 136786.93,
    "txCount": 2
  },
  {
    "date": "2022-10-03",
    "volume": 1890728.34,
    "txCount": 2
  },
  {
    "date": "2022-10-05",
    "volume": 92263.95,
    "txCount": 1
  },
  {
    "date": "2022-10-06",
    "volume": 940,
    "txCount": 1
  },
  {
    "date": "2022-10-08",
    "volume": 123577.77,
    "txCount": 1
  },
  {
    "date": "2022-10-09",
    "volume": 4479.84,
    "txCount": 1
  },
  {
    "date": "2022-10-11",
    "volume": 15415.2,
    "txCount": 1
  },
  {
    "date": "2022-10-13",
    "volume": 18.8,
    "txCount": 2
  },
  {
    "date": "2022-10-14",
    "volume": 5902.17,
    "txCount": 1
  },
  {
    "date": "2022-10-18",
    "volume": 9.4,
    "txCount": 1
  },
  {
    "date": "2022-10-22",
    "volume": 35365.52,
    "txCount": 1
  },
  {
    "date": "2022-10-24",
    "volume": 51700,
    "txCount": 2
  },
  {
    "date": "2022-10-25",
    "volume": 2326338.8,
    "txCount": 4
  },
  {
    "date": "2022-10-26",
    "volume": 121291.84,
    "txCount": 2
  },
  {
    "date": "2022-10-27",
    "volume": 940,
    "txCount": 1
  },
  {
    "date": "2022-10-28",
    "volume": 20902.78,
    "txCount": 2
  },
  {
    "date": "2022-10-29",
    "volume": 1715260.19,
    "txCount": 8
  },
  {
    "date": "2022-10-31",
    "volume": 1057213.46,
    "txCount": 5
  },
  {
    "date": "2022-11-01",
    "volume": 1296333.32,
    "txCount": 1
  },
  {
    "date": "2022-11-03",
    "volume": 84587.94,
    "txCount": 2
  },
  {
    "date": "2022-11-05",
    "volume": 23962.52,
    "txCount": 2
  },
  {
    "date": "2022-11-07",
    "volume": 4021.94,
    "txCount": 4
  },
  {
    "date": "2022-11-08",
    "volume": 3919.71,
    "txCount": 1
  },
  {
    "date": "2022-11-09",
    "volume": 1670030.91,
    "txCount": 3
  },
  {
    "date": "2022-11-13",
    "volume": 2846455.33,
    "txCount": 5
  },
  {
    "date": "2022-11-14",
    "volume": 1550956.51,
    "txCount": 4
  },
  {
    "date": "2022-11-17",
    "volume": 171093.76,
    "txCount": 1
  },
  {
    "date": "2022-11-21",
    "volume": 1724277.67,
    "txCount": 5
  },
  {
    "date": "2022-11-22",
    "volume": 59115664.08,
    "txCount": 27
  },
  {
    "date": "2022-11-23",
    "volume": 73213396.85,
    "txCount": 33
  },
  {
    "date": "2022-11-24",
    "volume": 1172507.9,
    "txCount": 1
  },
  {
    "date": "2022-11-25",
    "volume": 461589.21,
    "txCount": 1
  },
  {
    "date": "2022-11-26",
    "volume": 2439958.56,
    "txCount": 4
  },
  {
    "date": "2022-11-27",
    "volume": 536.39,
    "txCount": 1
  },
  {
    "date": "2022-11-28",
    "volume": 1500542.29,
    "txCount": 1
  },
  {
    "date": "2022-11-29",
    "volume": 1481577.02,
    "txCount": 1
  },
  {
    "date": "2022-12-01",
    "volume": 9811.15,
    "txCount": 1
  },
  {
    "date": "2022-12-03",
    "volume": 3577559.44,
    "txCount": 2
  },
  {
    "date": "2022-12-06",
    "volume": 158760.07,
    "txCount": 2
  },
  {
    "date": "2022-12-08",
    "volume": 170480.5,
    "txCount": 4
  },
  {
    "date": "2022-12-09",
    "volume": 3926496.24,
    "txCount": 1
  },
  {
    "date": "2022-12-10",
    "volume": 319144.81,
    "txCount": 2
  },
  {
    "date": "2022-12-11",
    "volume": 1425277.35,
    "txCount": 2
  },
  {
    "date": "2022-12-12",
    "volume": 5617.27,
    "txCount": 1
  },
  {
    "date": "2022-12-13",
    "volume": 749677.98,
    "txCount": 11
  },
  {
    "date": "2022-12-19",
    "volume": 1570372.95,
    "txCount": 1
  },
  {
    "date": "2022-12-20",
    "volume": 1152124.33,
    "txCount": 2
  },
  {
    "date": "2022-12-27",
    "volume": 6450.03,
    "txCount": 1
  },
  {
    "date": "2022-12-29",
    "volume": 10051.25,
    "txCount": 1
  },
  {
    "date": "2022-12-31",
    "volume": 96470.54,
    "txCount": 1
  },
  {
    "date": "2023-01-09",
    "volume": 11393.9,
    "txCount": 1
  },
  {
    "date": "2023-01-10",
    "volume": 19282.44,
    "txCount": 2
  },
  {
    "date": "2023-01-15",
    "volume": 368729.89,
    "txCount": 27
  },
  {
    "date": "2023-01-18",
    "volume": 46875.75,
    "txCount": 2
  },
  {
    "date": "2023-01-19",
    "volume": 764.88,
    "txCount": 1
  },
  {
    "date": "2023-01-20",
    "volume": 15168.73,
    "txCount": 3
  },
  {
    "date": "2023-01-21",
    "volume": 97515.03,
    "txCount": 2
  },
  {
    "date": "2023-01-22",
    "volume": 1799.86,
    "txCount": 1
  },
  {
    "date": "2023-01-23",
    "volume": 844220.82,
    "txCount": 4
  },
  {
    "date": "2023-01-25",
    "volume": 4610935.11,
    "txCount": 2
  },
  {
    "date": "2023-01-26",
    "volume": 2393.6,
    "txCount": 1
  },
  {
    "date": "2023-01-31",
    "volume": 6615852.7,
    "txCount": 3
  },
  {
    "date": "2023-02-05",
    "volume": 6145758.54,
    "txCount": 1
  },
  {
    "date": "2023-02-07",
    "volume": 47089.97,
    "txCount": 1
  },
  {
    "date": "2023-02-11",
    "volume": 58275.46,
    "txCount": 3
  },
  {
    "date": "2023-02-12",
    "volume": 16312.93,
    "txCount": 1
  },
  {
    "date": "2023-02-19",
    "volume": 13076434.94,
    "txCount": 1
  },
  {
    "date": "2023-02-27",
    "volume": 15114599.12,
    "txCount": 3
  },
  {
    "date": "2023-03-05",
    "volume": 661801.51,
    "txCount": 9
  },
  {
    "date": "2023-03-10",
    "volume": 4143.65,
    "txCount": 1
  },
  {
    "date": "2023-03-13",
    "volume": 7061730.82,
    "txCount": 1
  },
  {
    "date": "2023-03-14",
    "volume": 357303.34,
    "txCount": 2
  },
  {
    "date": "2023-03-17",
    "volume": 372595.26,
    "txCount": 3
  },
  {
    "date": "2023-03-27",
    "volume": 2068000,
    "txCount": 1
  },
  {
    "date": "2023-03-30",
    "volume": 940000,
    "txCount": 1
  },
  {
    "date": "2023-04-01",
    "volume": 13073.75,
    "txCount": 1
  },
  {
    "date": "2023-04-03",
    "volume": 1443796.37,
    "txCount": 1
  },
  {
    "date": "2023-04-04",
    "volume": 7059006.42,
    "txCount": 2
  },
  {
    "date": "2023-04-07",
    "volume": 67045.4,
    "txCount": 1
  },
  {
    "date": "2023-04-09",
    "volume": 770000,
    "txCount": 2
  },
  {
    "date": "2023-04-10",
    "volume": 92342.97,
    "txCount": 2
  },
  {
    "date": "2023-04-11",
    "volume": 24136.12,
    "txCount": 1
  },
  {
    "date": "2023-04-12",
    "volume": 3082530.78,
    "txCount": 3
  },
  {
    "date": "2023-04-13",
    "volume": 592014.04,
    "txCount": 2
  },
  {
    "date": "2023-04-14",
    "volume": 3290000,
    "txCount": 1
  },
  {
    "date": "2023-04-15",
    "volume": 893.94,
    "txCount": 1
  },
  {
    "date": "2023-04-16",
    "volume": 12299446.35,
    "txCount": 3
  },
  {
    "date": "2023-04-17",
    "volume": 733609.13,
    "txCount": 5
  },
  {
    "date": "2023-04-21",
    "volume": 16299.6,
    "txCount": 1
  },
  {
    "date": "2023-04-27",
    "volume": 1500.84,
    "txCount": 1
  },
  {
    "date": "2023-04-28",
    "volume": 169346.09,
    "txCount": 2
  },
  {
    "date": "2023-05-01",
    "volume": 669926.5,
    "txCount": 8
  },
  {
    "date": "2023-05-04",
    "volume": 493768.6,
    "txCount": 2
  },
  {
    "date": "2023-05-05",
    "volume": 3556.28,
    "txCount": 1
  },
  {
    "date": "2023-05-06",
    "volume": 11706.17,
    "txCount": 1
  },
  {
    "date": "2023-05-08",
    "volume": 8363.21,
    "txCount": 1
  },
  {
    "date": "2023-05-12",
    "volume": 6447.51,
    "txCount": 1
  },
  {
    "date": "2023-05-16",
    "volume": 5558874.88,
    "txCount": 68
  },
  {
    "date": "2023-05-19",
    "volume": 54593.18,
    "txCount": 1
  },
  {
    "date": "2023-05-21",
    "volume": 6944239.58,
    "txCount": 3
  },
  {
    "date": "2023-05-24",
    "volume": 1206297.64,
    "txCount": 1
  },
  {
    "date": "2023-05-26",
    "volume": 162.37,
    "txCount": 1
  },
  {
    "date": "2023-05-28",
    "volume": 6304.33,
    "txCount": 1
  },
  {
    "date": "2023-05-29",
    "volume": 119382.55,
    "txCount": 2
  },
  {
    "date": "2023-06-01",
    "volume": 3295754.86,
    "txCount": 1
  },
  {
    "date": "2023-06-07",
    "volume": 348648.93,
    "txCount": 1
  },
  {
    "date": "2023-06-16",
    "volume": 1411.42,
    "txCount": 1
  },
  {
    "date": "2023-06-23",
    "volume": 90850.05,
    "txCount": 1
  },
  {
    "date": "2023-07-06",
    "volume": 19081.23,
    "txCount": 1
  },
  {
    "date": "2023-07-11",
    "volume": 17936.37,
    "txCount": 1
  },
  {
    "date": "2023-07-13",
    "volume": 38316.49,
    "txCount": 1
  },
  {
    "date": "2023-07-28",
    "volume": 857,
    "txCount": 1
  },
  {
    "date": "2023-08-10",
    "volume": 9311.54,
    "txCount": 1
  },
  {
    "date": "2023-08-11",
    "volume": 8752.85,
    "txCount": 1
  },
  {
    "date": "2023-08-13",
    "volume": 10628.33,
    "txCount": 1
  },
  {
    "date": "2023-08-14",
    "volume": 108367.21,
    "txCount": 1
  },
  {
    "date": "2023-08-20",
    "volume": 249435.82,
    "txCount": 3
  },
  {
    "date": "2023-09-01",
    "volume": 527.79,
    "txCount": 1
  },
  {
    "date": "2023-09-19",
    "volume": 133835.67,
    "txCount": 2
  },
  {
    "date": "2023-09-20",
    "volume": 2777890.75,
    "txCount": 1
  },
  {
    "date": "2023-09-29",
    "volume": 7093.5,
    "txCount": 1
  },
  {
    "date": "2023-10-07",
    "volume": 259.01,
    "txCount": 1
  },
  {
    "date": "2023-10-24",
    "volume": 4261793.21,
    "txCount": 1
  },
  {
    "date": "2023-10-31",
    "volume": 332079.37,
    "txCount": 3
  },
  {
    "date": "2023-11-07",
    "volume": 18164.27,
    "txCount": 1
  },
  {
    "date": "2023-11-28",
    "volume": 282000,
    "txCount": 2
  },
  {
    "date": "2023-12-01",
    "volume": 0,
    "txCount": 1
  },
  {
    "date": "2023-12-03",
    "volume": 9743.61,
    "txCount": 2
  },
  {
    "date": "2023-12-04",
    "volume": 18800,
    "txCount": 1
  },
  {
    "date": "2023-12-09",
    "volume": 5432454.78,
    "txCount": 45
  },
  {
    "date": "2023-12-27",
    "volume": 3200406.81,
    "txCount": 14
  },
  {
    "date": "2023-12-28",
    "volume": 6223.55,
    "txCount": 1
  },
  {
    "date": "2024-01-02",
    "volume": 6682.63,
    "txCount": 1
  },
  {
    "date": "2024-01-05",
    "volume": 4355.12,
    "txCount": 1
  },
  {
    "date": "2024-01-06",
    "volume": 4288.46,
    "txCount": 1
  },
  {
    "date": "2024-01-10",
    "volume": 81022.36,
    "txCount": 1
  },
  {
    "date": "2024-01-13",
    "volume": 33131.58,
    "txCount": 2
  },
  {
    "date": "2024-01-16",
    "volume": 107440.07,
    "txCount": 1
  },
  {
    "date": "2024-02-04",
    "volume": 5929.02,
    "txCount": 1
  },
  {
    "date": "2024-02-08",
    "volume": 116.51,
    "txCount": 1
  },
  {
    "date": "2024-02-09",
    "volume": 5529.24,
    "txCount": 1
  },
  {
    "date": "2024-02-13",
    "volume": 2479.84,
    "txCount": 1
  },
  {
    "date": "2024-02-16",
    "volume": 4007384.65,
    "txCount": 1
  },
  {
    "date": "2024-02-18",
    "volume": 734599.06,
    "txCount": 6
  },
  {
    "date": "2024-02-22",
    "volume": 87749.19,
    "txCount": 2
  },
  {
    "date": "2024-02-23",
    "volume": 16942.93,
    "txCount": 1
  },
  {
    "date": "2024-02-27",
    "volume": 11224.66,
    "txCount": 1
  },
  {
    "date": "2024-02-28",
    "volume": 5368.89,
    "txCount": 1
  },
  {
    "date": "2024-03-02",
    "volume": 15462.03,
    "txCount": 1
  },
  {
    "date": "2024-03-06",
    "volume": 101849.54,
    "txCount": 2
  },
  {
    "date": "2024-03-07",
    "volume": 11480.48,
    "txCount": 1
  },
  {
    "date": "2024-03-10",
    "volume": 12055.11,
    "txCount": 1
  },
  {
    "date": "2024-03-12",
    "volume": 3877.74,
    "txCount": 1
  },
  {
    "date": "2024-03-13",
    "volume": 42578.36,
    "txCount": 2
  },
  {
    "date": "2024-03-18",
    "volume": 33468.66,
    "txCount": 1
  },
  {
    "date": "2024-03-19",
    "volume": 4137.7,
    "txCount": 1
  },
  {
    "date": "2024-03-20",
    "volume": 48324.24,
    "txCount": 2
  },
  {
    "date": "2024-03-26",
    "volume": 10812.35,
    "txCount": 1
  },
  {
    "date": "2024-04-07",
    "volume": 293504.72,
    "txCount": 4
  },
  {
    "date": "2024-04-08",
    "volume": 4074.24,
    "txCount": 1
  },
  {
    "date": "2024-04-15",
    "volume": 70249.46,
    "txCount": 1
  },
  {
    "date": "2024-04-16",
    "volume": 10769.83,
    "txCount": 1
  },
  {
    "date": "2024-04-17",
    "volume": 23918.48,
    "txCount": 15
  },
  {
    "date": "2024-04-22",
    "volume": 22483.38,
    "txCount": 1
  },
  {
    "date": "2024-04-27",
    "volume": 13768.96,
    "txCount": 2
  },
  {
    "date": "2024-04-28",
    "volume": 1932.43,
    "txCount": 1
  },
  {
    "date": "2024-05-01",
    "volume": 26030.06,
    "txCount": 1
  },
  {
    "date": "2024-05-02",
    "volume": 406974.77,
    "txCount": 4
  },
  {
    "date": "2024-05-04",
    "volume": 47867.45,
    "txCount": 2
  },
  {
    "date": "2024-05-16",
    "volume": 19760.66,
    "txCount": 5
  },
  {
    "date": "2024-05-27",
    "volume": 75755.38,
    "txCount": 2
  },
  {
    "date": "2024-06-05",
    "volume": 907.6,
    "txCount": 1
  },
  {
    "date": "2024-06-08",
    "volume": 981.87,
    "txCount": 1
  },
  {
    "date": "2024-06-11",
    "volume": 73776.85,
    "txCount": 2
  },
  {
    "date": "2024-06-27",
    "volume": 13177592.2,
    "txCount": 142
  },
  {
    "date": "2024-07-04",
    "volume": 492.11,
    "txCount": 1
  },
  {
    "date": "2024-07-05",
    "volume": 1431.77,
    "txCount": 2
  },
  {
    "date": "2024-07-06",
    "volume": 12604.12,
    "txCount": 1
  },
  {
    "date": "2024-07-10",
    "volume": 361.23,
    "txCount": 1
  },
  {
    "date": "2024-07-15",
    "volume": 382.81,
    "txCount": 1
  },
  {
    "date": "2024-07-21",
    "volume": 1085.45,
    "txCount": 1
  },
  {
    "date": "2024-07-22",
    "volume": 1011.19,
    "txCount": 1
  },
  {
    "date": "2024-07-25",
    "volume": 11351.71,
    "txCount": 5
  },
  {
    "date": "2024-07-28",
    "volume": 680084.05,
    "txCount": 3
  },
  {
    "date": "2024-08-01",
    "volume": 24803.69,
    "txCount": 1
  },
  {
    "date": "2024-08-02",
    "volume": 923.26,
    "txCount": 1
  },
  {
    "date": "2024-08-08",
    "volume": 308714.7,
    "txCount": 3
  },
  {
    "date": "2024-08-09",
    "volume": 331.84,
    "txCount": 1
  },
  {
    "date": "2024-08-10",
    "volume": 349.36,
    "txCount": 1
  },
  {
    "date": "2024-08-12",
    "volume": 284.31,
    "txCount": 1
  },
  {
    "date": "2024-08-18",
    "volume": 40.88,
    "txCount": 1
  },
  {
    "date": "2024-09-01",
    "volume": 37326.56,
    "txCount": 1
  },
  {
    "date": "2024-09-05",
    "volume": 13.72,
    "txCount": 1
  },
  {
    "date": "2024-09-07",
    "volume": 15.91,
    "txCount": 1
  },
  {
    "date": "2024-09-08",
    "volume": 49473.6,
    "txCount": 3
  },
  {
    "date": "2024-09-14",
    "volume": 14.27,
    "txCount": 1
  },
  {
    "date": "2024-09-21",
    "volume": 17.51,
    "txCount": 1
  },
  {
    "date": "2024-09-22",
    "volume": 1074.3,
    "txCount": 1
  },
  {
    "date": "2024-09-26",
    "volume": 1056.92,
    "txCount": 1
  },
  {
    "date": "2024-10-03",
    "volume": 1527811.69,
    "txCount": 22
  },
  {
    "date": "2024-10-07",
    "volume": 4054.84,
    "txCount": 1
  },
  {
    "date": "2024-10-10",
    "volume": 1206.4,
    "txCount": 2
  },
  {
    "date": "2024-10-18",
    "volume": 722.87,
    "txCount": 1
  },
  {
    "date": "2024-10-20",
    "volume": 49425.71,
    "txCount": 1
  },
  {
    "date": "2024-10-22",
    "volume": 4293.02,
    "txCount": 4
  },
  {
    "date": "2024-10-24",
    "volume": 101558.64,
    "txCount": 4
  },
  {
    "date": "2024-10-25",
    "volume": 0,
    "txCount": 4
  },
  {
    "date": "2024-10-26",
    "volume": 2539.24,
    "txCount": 2
  },
  {
    "date": "2024-10-27",
    "volume": 36863.09,
    "txCount": 2
  },
  {
    "date": "2024-10-28",
    "volume": 70071.13,
    "txCount": 2
  },
  {
    "date": "2024-10-29",
    "volume": 114524.55,
    "txCount": 4
  },
  {
    "date": "2024-10-30",
    "volume": 51891.12,
    "txCount": 3
  },
  {
    "date": "2024-10-31",
    "volume": 102962.19,
    "txCount": 3
  },
  {
    "date": "2024-11-02",
    "volume": 8.1,
    "txCount": 1
  },
  {
    "date": "2024-11-04",
    "volume": 8930.69,
    "txCount": 2
  },
  {
    "date": "2024-11-05",
    "volume": 40816.42,
    "txCount": 3
  },
  {
    "date": "2024-11-06",
    "volume": 6117.53,
    "txCount": 1
  },
  {
    "date": "2024-11-07",
    "volume": 1542330.96,
    "txCount": 27
  },
  {
    "date": "2024-11-08",
    "volume": 98048.29,
    "txCount": 11
  },
  {
    "date": "2024-11-09",
    "volume": 53769.26,
    "txCount": 12
  },
  {
    "date": "2024-11-10",
    "volume": 259547.21,
    "txCount": 3
  },
  {
    "date": "2024-11-12",
    "volume": 1627.89,
    "txCount": 1
  },
  {
    "date": "2024-11-13",
    "volume": 67268.37,
    "txCount": 3
  },
  {
    "date": "2024-11-14",
    "volume": 2758188.19,
    "txCount": 27
  },
  {
    "date": "2024-11-15",
    "volume": 381582.66,
    "txCount": 28
  },
  {
    "date": "2024-11-17",
    "volume": 15386.89,
    "txCount": 2
  },
  {
    "date": "2024-11-18",
    "volume": 39870.3,
    "txCount": 4
  },
  {
    "date": "2024-11-19",
    "volume": 18159.36,
    "txCount": 1
  },
  {
    "date": "2024-11-20",
    "volume": 114726.83,
    "txCount": 6
  },
  {
    "date": "2024-11-21",
    "volume": 99114.53,
    "txCount": 13
  },
  {
    "date": "2024-11-22",
    "volume": 145609.29,
    "txCount": 7
  },
  {
    "date": "2024-11-23",
    "volume": 42591.72,
    "txCount": 1
  },
  {
    "date": "2024-11-24",
    "volume": 60884.11,
    "txCount": 16
  },
  {
    "date": "2024-11-25",
    "volume": 850659.27,
    "txCount": 15
  },
  {
    "date": "2024-11-26",
    "volume": 315769.78,
    "txCount": 8
  },
  {
    "date": "2024-11-27",
    "volume": 61920.19,
    "txCount": 4
  },
  {
    "date": "2024-11-28",
    "volume": 112245.71,
    "txCount": 20
  },
  {
    "date": "2024-11-29",
    "volume": 935831.43,
    "txCount": 15
  },
  {
    "date": "2024-11-30",
    "volume": 207648.26,
    "txCount": 22
  },
  {
    "date": "2024-12-01",
    "volume": 940644.9,
    "txCount": 19
  },
  {
    "date": "2024-12-02",
    "volume": 119634.06,
    "txCount": 8
  },
  {
    "date": "2024-12-03",
    "volume": 725175.81,
    "txCount": 14
  },
  {
    "date": "2024-12-04",
    "volume": 25086.94,
    "txCount": 8
  },
  {
    "date": "2024-12-05",
    "volume": 416281.73,
    "txCount": 22
  },
  {
    "date": "2024-12-06",
    "volume": 75181.16,
    "txCount": 10
  },
  {
    "date": "2024-12-07",
    "volume": 184213.55,
    "txCount": 5
  },
  {
    "date": "2024-12-08",
    "volume": 38635.13,
    "txCount": 8
  },
  {
    "date": "2024-12-09",
    "volume": 518083.27,
    "txCount": 17
  },
  {
    "date": "2024-12-10",
    "volume": 235174.67,
    "txCount": 9
  },
  {
    "date": "2024-12-11",
    "volume": 721629.49,
    "txCount": 20
  },
  {
    "date": "2024-12-12",
    "volume": 158855.52,
    "txCount": 5
  },
  {
    "date": "2024-12-13",
    "volume": 2592943.26,
    "txCount": 21
  },
  {
    "date": "2024-12-14",
    "volume": 261801.88,
    "txCount": 21
  },
  {
    "date": "2024-12-15",
    "volume": 1132459.56,
    "txCount": 32
  },
  {
    "date": "2024-12-16",
    "volume": 718958.92,
    "txCount": 5
  },
  {
    "date": "2024-12-17",
    "volume": 17180.1,
    "txCount": 5
  },
  {
    "date": "2024-12-18",
    "volume": 281472.78,
    "txCount": 29
  },
  {
    "date": "2024-12-20",
    "volume": 204128.78,
    "txCount": 8
  },
  {
    "date": "2024-12-21",
    "volume": 129322.99,
    "txCount": 17
  },
  {
    "date": "2024-12-22",
    "volume": 25834.25,
    "txCount": 2
  },
  {
    "date": "2024-12-23",
    "volume": 33067.29,
    "txCount": 3
  },
  {
    "date": "2024-12-24",
    "volume": 59093.67,
    "txCount": 9
  },
  {
    "date": "2024-12-25",
    "volume": 52806.09,
    "txCount": 3
  },
  {
    "date": "2024-12-29",
    "volume": 107256.97,
    "txCount": 5
  },
  {
    "date": "2024-12-30",
    "volume": 2170.7,
    "txCount": 1
  },
  {
    "date": "2024-12-31",
    "volume": 1443968.41,
    "txCount": 15
  },
  {
    "date": "2025-01-01",
    "volume": 12732.7,
    "txCount": 1
  },
  {
    "date": "2025-01-02",
    "volume": 25615.77,
    "txCount": 9
  },
  {
    "date": "2025-01-03",
    "volume": 21660.71,
    "txCount": 4
  },
  {
    "date": "2025-01-04",
    "volume": 2808.61,
    "txCount": 1
  },
  {
    "date": "2025-01-05",
    "volume": 47801.43,
    "txCount": 4
  },
  {
    "date": "2025-01-06",
    "volume": 73605.24,
    "txCount": 16
  },
  {
    "date": "2025-01-07",
    "volume": 742790.9,
    "txCount": 14
  },
  {
    "date": "2025-01-08",
    "volume": 22.46,
    "txCount": 1
  },
  {
    "date": "2025-01-09",
    "volume": 37144.6,
    "txCount": 6
  },
  {
    "date": "2025-01-10",
    "volume": 617816.7,
    "txCount": 18
  },
  {
    "date": "2025-01-11",
    "volume": 9735.01,
    "txCount": 4
  },
  {
    "date": "2025-01-12",
    "volume": 69762.84,
    "txCount": 10
  },
  {
    "date": "2025-01-13",
    "volume": 5975.57,
    "txCount": 2
  },
  {
    "date": "2025-01-14",
    "volume": 2798.9,
    "txCount": 1
  },
  {
    "date": "2025-01-15",
    "volume": 30352.93,
    "txCount": 13
  },
  {
    "date": "2025-01-16",
    "volume": 118403.88,
    "txCount": 13
  },
  {
    "date": "2025-01-17",
    "volume": 59720.63,
    "txCount": 10
  },
  {
    "date": "2025-01-18",
    "volume": 76123.59,
    "txCount": 10
  },
  {
    "date": "2025-01-19",
    "volume": 976061.74,
    "txCount": 22
  },
  {
    "date": "2025-01-20",
    "volume": 175650.14,
    "txCount": 13
  },
  {
    "date": "2025-01-21",
    "volume": 110380.15,
    "txCount": 16
  },
  {
    "date": "2025-01-22",
    "volume": 870871.56,
    "txCount": 21
  },
  {
    "date": "2025-01-23",
    "volume": 416858.88,
    "txCount": 5
  },
  {
    "date": "2025-01-24",
    "volume": 144689.79,
    "txCount": 14
  },
  {
    "date": "2025-01-26",
    "volume": 614286.92,
    "txCount": 29
  },
  {
    "date": "2025-01-27",
    "volume": 68033.91,
    "txCount": 5
  },
  {
    "date": "2025-01-28",
    "volume": 16105.89,
    "txCount": 5
  },
  {
    "date": "2025-01-29",
    "volume": 1045518.9,
    "txCount": 14
  },
  {
    "date": "2025-01-31",
    "volume": 861508.54,
    "txCount": 14
  },
  {
    "date": "2025-02-01",
    "volume": 289476.68,
    "txCount": 9
  },
  {
    "date": "2025-02-02",
    "volume": 838974.35,
    "txCount": 19
  },
  {
    "date": "2025-02-04",
    "volume": 11863.23,
    "txCount": 5
  },
  {
    "date": "2025-02-05",
    "volume": 1124.76,
    "txCount": 6
  },
  {
    "date": "2025-02-06",
    "volume": 14946.91,
    "txCount": 2
  },
  {
    "date": "2025-02-07",
    "volume": 35091.94,
    "txCount": 5
  },
  {
    "date": "2025-02-08",
    "volume": 29506.47,
    "txCount": 7
  },
  {
    "date": "2025-02-09",
    "volume": 218481.09,
    "txCount": 10
  },
  {
    "date": "2025-02-10",
    "volume": 253966.97,
    "txCount": 15
  },
  {
    "date": "2025-02-12",
    "volume": 11351.38,
    "txCount": 2
  },
  {
    "date": "2025-02-13",
    "volume": 26977.95,
    "txCount": 7
  },
  {
    "date": "2025-02-14",
    "volume": 68966.36,
    "txCount": 7
  },
  {
    "date": "2025-02-15",
    "volume": 21.41,
    "txCount": 1
  },
  {
    "date": "2025-02-16",
    "volume": 24902.06,
    "txCount": 6
  },
  {
    "date": "2025-02-17",
    "volume": 56360.37,
    "txCount": 7
  },
  {
    "date": "2025-02-18",
    "volume": 35879.67,
    "txCount": 5
  },
  {
    "date": "2025-02-19",
    "volume": 44030.31,
    "txCount": 5
  },
  {
    "date": "2025-02-20",
    "volume": 36307.04,
    "txCount": 6
  },
  {
    "date": "2025-02-22",
    "volume": 2313.45,
    "txCount": 1
  },
  {
    "date": "2025-02-25",
    "volume": 32226.06,
    "txCount": 3
  },
  {
    "date": "2025-02-26",
    "volume": 17443.5,
    "txCount": 1
  },
  {
    "date": "2025-02-27",
    "volume": 4405.18,
    "txCount": 2
  },
  {
    "date": "2025-02-28",
    "volume": 18533.89,
    "txCount": 2
  },
  {
    "date": "2025-03-02",
    "volume": 181787.01,
    "txCount": 2
  },
  {
    "date": "2025-03-03",
    "volume": 21488.99,
    "txCount": 3
  },
  {
    "date": "2025-03-09",
    "volume": 748.55,
    "txCount": 2
  },
  {
    "date": "2025-03-10",
    "volume": 69.34,
    "txCount": 1
  },
  {
    "date": "2025-03-16",
    "volume": 24904.58,
    "txCount": 6
  },
  {
    "date": "2025-03-17",
    "volume": 16236.63,
    "txCount": 3
  },
  {
    "date": "2025-03-18",
    "volume": 2162.05,
    "txCount": 1
  },
  {
    "date": "2025-03-23",
    "volume": 31.64,
    "txCount": 3
  },
  {
    "date": "2025-03-24",
    "volume": 50273.11,
    "txCount": 4
  },
  {
    "date": "2025-03-25",
    "volume": 1569.54,
    "txCount": 2
  },
  {
    "date": "2025-03-26",
    "volume": 689.52,
    "txCount": 2
  },
  {
    "date": "2025-03-29",
    "volume": 3293.98,
    "txCount": 1
  },
  {
    "date": "2025-03-31",
    "volume": 551254.61,
    "txCount": 4
  },
  {
    "date": "2025-04-03",
    "volume": 8416.03,
    "txCount": 2
  },
  {
    "date": "2025-04-09",
    "volume": 1015.35,
    "txCount": 1
  },
  {
    "date": "2025-04-13",
    "volume": 1933.16,
    "txCount": 2
  },
  {
    "date": "2025-04-14",
    "volume": 2844.52,
    "txCount": 1
  },
  {
    "date": "2025-04-16",
    "volume": 435.14,
    "txCount": 1
  },
  {
    "date": "2025-04-17",
    "volume": 1548.27,
    "txCount": 1
  },
  {
    "date": "2025-04-27",
    "volume": 12583.72,
    "txCount": 2
  },
  {
    "date": "2025-04-28",
    "volume": 170276.99,
    "txCount": 10
  },
  {
    "date": "2025-05-01",
    "volume": 940,
    "txCount": 1
  },
  {
    "date": "2025-05-02",
    "volume": 42989.72,
    "txCount": 4
  },
  {
    "date": "2025-05-12",
    "volume": 52065.01,
    "txCount": 4
  },
  {
    "date": "2025-05-15",
    "volume": 611.54,
    "txCount": 1
  },
  {
    "date": "2025-05-18",
    "volume": 5308.21,
    "txCount": 5
  },
  {
    "date": "2025-05-21",
    "volume": 1733.61,
    "txCount": 1
  },
  {
    "date": "2025-05-22",
    "volume": 12.26,
    "txCount": 1
  },
  {
    "date": "2025-05-24",
    "volume": 26955.6,
    "txCount": 5
  },
  {
    "date": "2025-05-28",
    "volume": 5702.09,
    "txCount": 4
  },
  {
    "date": "2025-05-29",
    "volume": 2704.17,
    "txCount": 3
  }
]